ks_trade_api/./.git
ks_trade_api/./.gitignore
ks_trade_api/./0.0.31
ks_trade_api/./1.26.1
ks_trade_api/./README.en.md
ks_trade_api/./README.md
ks_trade_api/./__about__.py
ks_trade_api/./__init__.py
ks_trade_api/./base_fundamental_api.py
ks_trade_api/./base_market_api.py
ks_trade_api/./base_trade_api.py
ks_trade_api/./constant.py
ks_trade_api/./global_rate_limit.py
ks_trade_api/./indicator.py
ks_trade_api/./object.py
ks_trade_api/./pyproject.toml
ks_trade_api/./rate_limit_checker.py
ks_trade_api/./requirements.txt
ks_trade_api/./setup.py
ks_trade_api/./utility.py
ks_trade_api/./volume_auto_adjust.py
ks_trade_api/./tests/test_utility.py
ks_trade_api-0.1.6.dist-info/METADATA
ks_trade_api-0.1.6.dist-info/WHEEL
ks_trade_api-0.1.6.dist-info/RECORD
