Metadata-Version: 2.4
Name: ks_trade_api
Version: 0.1.6
Project-URL: Documentation, https://github.com/unknown/ks-binance-api#readme
Project-URL: Issues, https://github.com/unknown/ks-binance-api/issues
Project-URL: Source, https://github.com/unknown/ks-binance-api
Author-email: liuyanzhi08 <702368372@qq.com>
Classifier: Development Status :: 4 - Beta
Classifier: Programming Language :: Python
Classifier: Programming Language :: Python :: 3.8
Classifier: Programming Language :: Python :: 3.9
Classifier: Programming Language :: Python :: 3.10
Classifier: Programming Language :: Python :: 3.11
Classifier: Programming Language :: Python :: 3.12
Classifier: Programming Language :: Python :: Implementation :: CPython
Classifier: Programming Language :: Python :: Implementation :: PyPy
Requires-Python: >=3.8
Requires-Dist: ks-utility>=0.0.41
